carafe/__init__.py
carafe/app.py
carafe/client.py
carafe/utils.py
carafe/__meta__.py
carafe/request.py
carafe/response.py
carafe/ext/__init__.py
carafe/ext/auth.py
carafe/ext/cache.py
carafe/ext/logger.py
carafe/ext/session.py
carafe-0.4.7.dist-info/top_level.txt
carafe-0.4.7.dist-info/METADATA
carafe-0.4.7.dist-info/DESCRIPTION.rst
carafe-0.4.7.dist-info/metadata.json
carafe-0.4.7.dist-info/WHEEL
carafe-0.4.7.dist-info/RECORD
