Metadata-Version: 2.0
Name: carafe
Version: 0.4.7
Summary: Collection of Flask extensions geared towards JSON APIs
Home-page: https://github.com/dgilland/carafe
Author: Derrick Gilland
Author-email: dgilland@gmail.com
License: MIT License
Keywords: flask
Platform: UNKNOWN
Classifier: Development Status :: 4 - Beta
Classifier: Environment :: Web Environment
Classifier: Intended Audience :: Developers
Classifier: Operating System :: OS Independent
Classifier: License :: OSI Approved :: MIT License
Classifier: Framework :: Flask
Classifier: Topic :: Internet :: WWW/HTTP :: Dynamic Content
Classifier: Topic :: Software Development :: Libraries :: Python Modules
Classifier: Programming Language :: Python
Classifier: Programming Language :: Python :: 2.7
Requires-Dist: Flask (>=0.10.1)
Requires-Dist: Flask-Cache (>=0.12)
Requires-Dist: Flask-Principal (>=0.4.0)
Requires-Dist: Flask-Testing (>=0.4)
Requires-Dist: blinker (>=1.3)
